README.txt
setup.py
django_imagequery.egg-info/PKG-INFO
django_imagequery.egg-info/SOURCES.txt
django_imagequery.egg-info/dependency_links.txt
django_imagequery.egg-info/not-zip-safe
django_imagequery.egg-info/requires.txt
django_imagequery.egg-info/top_level.txt
imagequery/__init__.py
imagequery/autoload.py
imagequery/formats.py
imagequery/models.py
imagequery/operations.py
imagequery/query.py
imagequery/settings.py
imagequery/urls.py
imagequery/utils.py
imagequery/views.py
imagequery/templatetags/__init__.py
imagequery/templatetags/imagequery_tags.py
imagequery/tests/__init__.py
imagequery/tests/samplefonts/Vera.ttf
imagequery/tests/samplefonts/VeraBI.ttf
imagequery/tests/samplefonts/VeraBd.ttf
imagequery/tests/samplefonts/VeraIt.ttf
imagequery/tests/samplefonts/VeraMoBI.ttf
imagequery/tests/samplefonts/VeraMoBd.ttf
imagequery/tests/samplefonts/VeraMoIt.ttf
imagequery/tests/samplefonts/VeraMono.ttf
imagequery/tests/samplefonts/VeraSe.ttf
imagequery/tests/samplefonts/VeraSeBd.ttf
imagequery/tests/sampleimages/django_colors.jpg
imagequery/tests/sampleimages/django_colors.png
imagequery/tests/sampleimages/lynx_kitten.jpg
imagequery/tests/sampleimages/tux_transparent.png
imagequery/tests/sampleimages/results/blank_100x100_250,200,150,100.png
imagequery/tests/sampleimages/results/django_colors_gray.jpg
imagequery/tests/sampleimages/results/django_colors_text_center_10.jpg
imagequery/tests/sampleimages/results/django_colors_with_tux_center_bottom.jpg
imagequery/tests/sampleimages/results/lynx_fit_400_160.jpg
imagequery/tests/sampleimages/results/lynx_kitten_mirror_flip_invert_resize_400_300.jpg
imagequery/tests/sampleimages/results/lynx_resize_400.jpg
imagequery/tests/sampleimages/results/lynx_resize_400_sharpness_-1.jpg
imagequery/tests/sampleimages/results/lynx_resize_400_sharpness_3.jpg
imagequery/tests/sampleimages/results/tux_blank_000088.png