Metadata-Version: 1.1
Name: django-imagequery
Version: 0.2.1
Summary: Image manipulation written like well known QuerySet operations
Home-page: https://github.com/ddanier/django_imagequery
Author: David Danier
Author-email: david.danier@team23.de
License: BSD License
Keywords: django imagequery PIL
Platform: UNKNOWN
Classifier: Intended Audience :: Developers
Classifier: License :: OSI Approved :: BSD License
Classifier: Operating System :: OS Independent
Classifier: Programming Language :: Python
Classifier: Framework :: Django
Classifier: Topic :: Utilities
